tagpack/__init__.py
tagpack/actorpack.py
tagpack/actorpack_schema.py
tagpack/cli.py
tagpack/cmd_utils.py
tagpack/concept_mapping.py
tagpack/confidence.py
tagpack/constants.py
tagpack/graphsense.py
tagpack/schema.py
tagpack/tagpack.py
tagpack/tagpack_schema.py
tagpack/tagstore.py
tagpack/taxonomy.py
tagpack/utils.py
tagpack/conf/__init__.py
tagpack/conf/actorpack_schema.yaml
tagpack/conf/ks_map.json.template
tagpack/conf/tagpack_schema.yaml
tagpack/db/__init__.py
tagpack/db/concept_relation_annotation.csv
tagpack/db/concepts.yaml
tagpack/db/confidence.csv
tagpack/db/countries.csv
tagpack/db/tag_subject.csv
tagpack/db/tag_types.csv
tagpack_tool-25.8.1.dist-info/licenses/LICENSE
tagstore/__init__.py
tagstore/algorithms/__init__.py
tagstore/algorithms/tag_digest.py
tagstore/cli/__init__.py
tagstore/cli/main.py
tagstore/config/__init__.py
tagstore/db/__init__.py
tagstore/db/database.py
tagstore/db/errors.py
tagstore/db/init.sql
tagstore/db/models.py
tagstore/db/queries.py
tagstore/web/__init__.py
tagstore/web/dependencies.py
tagstore/web/main.py
tagstore/web/routers/__init__.py
tagstore/web/routers/admin.py
tagstore/web/routers/base.py
tagstore/web/statics/__init__.py
tagstore/web/statics/index.html
tagstore/web/statics/assets/__init__.py
tagstore/web/statics/assets/index.js
tagpack_tool-25.8.1.dist-info/METADATA
tagpack_tool-25.8.1.dist-info/WHEEL
tagpack_tool-25.8.1.dist-info/entry_points.txt
tagpack_tool-25.8.1.dist-info/top_level.txt
tagpack_tool-25.8.1.dist-info/RECORD
