Metadata-Version: 2.4
Name: tagpack-tool
Version: 25.8.1
Summary: GraphSense TagPack Management Tool
Author-email: GraphSense Core Team <tech@ikna.io>
Project-URL: Source, https://github.com/graphsense/graphsense-tagpack-tool
Project-URL: Repository, https://github.com/graphsense/graphsense-tagpack-tool.git
Project-URL: Changelog, https://github.com/graphsense/graphsense-tagpack-tool/blob/master/CHANGELOG.md
Project-URL: Tracker, https://github.com/graphsense/graphsense-tagpack-tool/issues
Project-URL: Download, https://github.com/graphsense
Keywords: graphsense
Classifier: Programming Language :: Python :: 3
Classifier: Operating System :: OS Independent
Classifier: Intended Audience :: Developers
Classifier: Topic :: Utilities
Requires-Python: >=3.9
License-File: LICENSE
Requires-Dist: anytree>=2.9.0
Requires-Dist: asyncpg>=0.30.0
Requires-Dist: base58>=2.1
Requires-Dist: cashaddress>=1.0.4
Requires-Dist: cassandra-driver>=3.27.0
Requires-Dist: coinaddrvalidator>=1.2.3
Requires-Dist: colorama>=0.4.6
Requires-Dist: fastapi[all]>=0.101.0
Requires-Dist: gitpython>=3.1
Requires-Dist: giturlparse>=0.10
Requires-Dist: lz4>=4.3.2
Requires-Dist: pandas>=1.3.5
Requires-Dist: psycopg2-binary>=2.9.3
Requires-Dist: python-dotenv>=1.0.1
Requires-Dist: pyyaml-include~=1.3
Requires-Dist: pyyaml>=6.0
Requires-Dist: requests>=2.28.1
Requires-Dist: sqlmodel>=0.0.22
Requires-Dist: tabulate>=0.9.0
Requires-Dist: typer>=0.13.0
Dynamic: license-file
